ipwt_pi/__init__.py
ipwt_pi/pi_monitor.py
ipwt_pi-0.1.0.dist-info/METADATA
ipwt_pi-0.1.0.dist-info/WHEEL
ipwt_pi-0.1.0.dist-info/licenses/LICENSE
ipwt_pi-0.1.0.dist-info/RECORD
