Metadata-Version: 2.4
Name: ipwt-pi
Version: 0.1.0
Summary: A lightweight tool to calculate Predictive Integrity (PI) for PyTorch models.
Project-URL: Homepage, https://github.com/dmf-archive/pi-monitor
Project-URL: Bug Tracker, https://github.com/dmf-archive/pi-monitor/issues
Author-email: dmf-archive <Lin.Rui.ipwt@proton.me>
License: MIT License
License-File: LICENSE
Classifier: Development Status :: 3 - Alpha
Classifier: Intended Audience :: Developers
Classifier: Intended Audience :: Science/Research
Classifier: License :: OSI Approved :: MIT License
Classifier: Operating System :: OS Independent
Classifier: Programming Language :: Python :: 3
Classifier: Programming Language :: Python :: 3.8
Classifier: Programming Language :: Python :: 3.9
Classifier: Programming Language :: Python :: 3.10
Classifier: Programming Language :: Python :: 3.11
Classifier: Programming Language :: Python :: 3.12
Classifier: Topic :: Scientific/Engineering :: Artificial Intelligence
Classifier: Topic :: Software Development :: Libraries :: Python Modules
Requires-Python: >=3.8
Requires-Dist: hatch>=1.14.1
Requires-Dist: mypy>=1.14.1
Requires-Dist: torch>=2.5.1
Requires-Dist: torchvision>=0.20.1
